{"transacao":{"tid":"100699306930C30C1001","pan":"f7SXq1Xk16jOBFdZVwAXmGEH8VnfEfLRstUaR4gfqf4=","dados-pedido":{"numero":"12","valor":"1200","moeda":"986","data-hora":"2015-07-08T16:11:46.114-03:00","idioma":"PT","taxa-embarque":"0"},"forma-pagamento":{"bandeira":"visa","produto":"1","parcelas":"1"},"status":"9","autenticacao":{"codigo":"9","mensagem":"Transacao sem autenticacao","data-hora":"2015-07-08T16:11:46.123-03:00","valor":"1200","eci":"7"},"autorizacao":{"codigo":"9","mensagem":"Transação autorizada","data-hora":"2015-07-08T16:11:46.127-03:00","valor":"1200","lr":"00","arp":"123456","nsu":"195660"},"captura":{"codigo":"9","mensagem":"Transacao capturada com sucesso","data-hora":"2015-07-08T16:11:46.164-03:00","valor":"1200"},"cancelamentos":{"cancelamento":{"codigo":"9","mensagem":"Transacao cancelada com sucesso","data-hora":"2015-07-08T16:27:30.647-03:00","valor":"1200"}}}}